concall_parser/__init__.py
concall_parser/agents/__init__.py
concall_parser/agents/check_moderator.py
concall_parser/agents/classify.py
concall_parser/agents/extraction.py
concall_parser/agents/verify_speakers.py
concall_parser/base_parser.py
concall_parser/config.py
concall_parser/extractors/__init__.py
concall_parser/extractors/dialogue_extractor.py
concall_parser/extractors/management.py
concall_parser/extractors/management_case_extractor.py
concall_parser/log_config.py
concall_parser/parser.py
concall_parser/utils/__init__.py
concall_parser/utils/cleaner.py
concall_parser/utils/file_utils.py
concall_parser/utils/get_groq_responses.py
concall_parser-1.1.1.dist-info/METADATA
concall_parser-1.1.1.dist-info/WHEEL
concall_parser-1.1.1.dist-info/licenses/LICENSE
concall_parser-1.1.1.dist-info/RECORD
