Metadata-Version: 2.4
Name: concall-parser
Version: 1.1.1
Summary: A parser for extracting analyst discussion and management commentary efficiently from concalls.
License-File: LICENSE
Author: Jay Shah
Author-email: jayshah0726@gmail.com
Maintainer: Pranshu Raj
Maintainer-email: pranshuraj65536@gmail.com
Requires-Python: >=3.12,<4.0
Classifier: Programming Language :: Python :: 3
Classifier: Programming Language :: Python :: 3.12
Classifier: Programming Language :: Python :: 3.13
Classifier: Programming Language :: Python :: 3.14
Requires-Dist: groq-sdk (==0.9.0)
Requires-Dist: pdfplumber (==0.11.8)
Requires-Dist: python-dotenv (==1.2.1)
Requires-Dist: requests (==2.32.5)
